Metadata-Version: 1.1
Name: django-mssql-backend
Version: 2.8.1
Summary: Django backend for Microsoft SQL Server
Home-page: https://github.com/ESSolutions/django-mssql-backend
Author: ES Solutions AB
Author-email: info@essolutions.se
License: BSD
Keywords: django
Platform: UNKNOWN
Classifier: License :: OSI Approved :: BSD License
Classifier: Framework :: Django
Classifier: Operating System :: POSIX :: Linux
Classifier: Operating System :: Microsoft :: Windows
Classifier: Programming Language :: Python
Classifier: Programming Language :: Python :: 3
Classifier: Programming Language :: Python :: 3.5
Classifier: Programming Language :: Python :: 3.6
Classifier: Programming Language :: Python :: 3.7
Classifier: Framework :: Django :: 2.2
Classifier: Framework :: Django :: 3.0
